arycodes/__init__.py
arycodes/arycodes_cli.py
arycodes-0.2.1.dist-info/licenses/LICENSE
arycodes-0.2.1.dist-info/METADATA
arycodes-0.2.1.dist-info/WHEEL
arycodes-0.2.1.dist-info/entry_points.txt
arycodes-0.2.1.dist-info/top_level.txt
arycodes-0.2.1.dist-info/RECORD
